physical2logical/__init__.py
physical2logical/__main__.py
physical2logical/aligner.py
physical2logical/analyze.py
physical2logical/arguments.py
physical2logical/commons.py
physical2logical/config.py
physical2logical/logger.py
physical2logical/process_files.py
physical2logical/renamer.py
physical2logical/replacer.py
physical2logical/tokenize_values.py
physical2logical-2.3.1.dist-info/LICENSE
physical2logical-2.3.1.dist-info/METADATA
physical2logical-2.3.1.dist-info/WHEEL
physical2logical-2.3.1.dist-info/entry_points.txt
physical2logical-2.3.1.dist-info/top_level.txt
physical2logical-2.3.1.dist-info/RECORD
