Metadata-Version: 2.1
Name: physical2logical
Version: 2.3.1
Summary: Convert CSS physical properties to logical
Author-email: Dragan Filipovic <info@frontenddot.com>, Yuri Astrakhan <yuriastrakhan@gmail.com>
License: Apache Software License
Keywords: css,rtl,logical,physical,scss
License-File: LICENSE
